.npmignore
README.md
calc_npm_version.py
index.js
package.json
set_npm_version.sh
setup.py
scripts/merge_abis.py
tlbin/__init__.py
tlbin/contracts.json
tlbin/contracts.py
tlbin/legacy_currency_networks.json
tlbin/merged_abis.json
trustlines_contracts_bin.egg-info/PKG-INFO
trustlines_contracts_bin.egg-info/SOURCES.txt
trustlines_contracts_bin.egg-info/dependency_links.txt
trustlines_contracts_bin.egg-info/top_level.txt