Metadata-Version: 2.1
Name: trustlines-contracts-bin
Version: 2.0.0
Summary: Smart Contracts for Trustlines-Network
Home-page: https://github.com/trustlines-protocol/contracts
Author: Trustlines-Network
Author-email: contact@brainbot.com
License: MIT
Keywords: trustlines
Platform: UNKNOWN
Classifier: Development Status :: 2 - Pre-Alpha
Classifier: Intended Audience :: Developers
Classifier: License :: OSI Approved :: MIT License
Classifier: Programming Language :: Python :: 3
Classifier: Programming Language :: Python :: 3.5
Classifier: Programming Language :: Python :: 3.6
